magicimg/__init__.py
magicimg/cli.py
magicimg/core.py
magicimg/utils.py
magicimg-1.0.10.dist-info/LICENSE
magicimg-1.0.10.dist-info/METADATA
magicimg-1.0.10.dist-info/WHEEL
magicimg-1.0.10.dist-info/entry_points.txt
magicimg-1.0.10.dist-info/top_level.txt
magicimg-1.0.10.dist-info/RECORD
