Metadata-Version: 2.1
Name: magicimg
Version: 1.0.10
Summary: Thư viện xử lý và tiền xử lý ảnh cho OCR
Home-page: https://github.com/magicimg/magicimg
Author: MagicImg Team
Author-email: MagicImg Team <contact@magicimg.com>
License: MIT
Project-URL: Homepage, https://github.com/magicimg/magicimg
Classifier: Programming Language :: Python :: 3
Classifier: Operating System :: OS Independent
Requires-Python: >=3.7
License-File: LICENSE
Requires-Dist: opencv-python>=4.5.0
Requires-Dist: numpy>=1.19.0
Requires-Dist: matplotlib>=3.3.0
Requires-Dist: Pillow>=8.0.0
Requires-Dist: pytesseract>=0.3.0
Provides-Extra: dev
Requires-Dist: pytest>=6.2.0; extra == "dev"
Requires-Dist: pytest-cov>=2.12.0; extra == "dev"
Requires-Dist: black>=21.5b2; extra == "dev"
Requires-Dist: isort>=5.9.1; extra == "dev"
Requires-Dist: flake8>=3.9.2; extra == "dev"
